gpt/__init__.py
gpt/scripts.py
gpt-0.1.dist-info/LICENSE
gpt-0.1.dist-info/METADATA
gpt-0.1.dist-info/WHEEL
gpt-0.1.dist-info/entry_points.txt
gpt-0.1.dist-info/top_level.txt
gpt-0.1.dist-info/RECORD
